helpful_assistant/__init__.py
helpful_assistant/action.py
helpful_assistant/assistant.py
helpful_assistant/conversation.py
helpful_assistant/events.py
helpful_assistant/module.py
helpful_assistant/stream.py
helpful_assistant-0.1.0.dist-info/LICENSE
helpful_assistant-0.1.0.dist-info/METADATA
helpful_assistant-0.1.0.dist-info/WHEEL
helpful_assistant-0.1.0.dist-info/top_level.txt
helpful_assistant-0.1.0.dist-info/RECORD
