Metadata-Version: 2.1
Name: helpful-assistant
Version: 0.1.0
Summary: Allows LLMs to assist you with various tasks, all while being open-source!
Author: Whitelisted
Project-URL: Homepage, https://github.com/Whitelisted1/Helpful-Assistant
Project-URL: Issues, https://github.com/Whitelisted1/Helpful-Assistant/issues
Classifier: Programming Language :: Python :: 3
Classifier: License :: OSI Approved :: GNU Affero General Public License v3
Classifier: Operating System :: OS Independent
Requires-Python: >=3.8
License-File: LICENSE
